Metadata-Version: 1.0
Name: word-distance
Version: 0.1.0
Summary: word distance wrapper for log analysis
Home-page: UNKNOWN
Author: Rui Ren
Author-email: UNKNOWN
License: UNKNOWN
Platform: UNKNOWN
